AUTHORS.rst
CHANGES.rst
LICENSE.txt
MANIFEST.in
README.rst
dev-requirements.txt
requirements.txt
setup.py
docs/conf.py
docs/index.rst
purkinje/__init__.py
purkinje/app.py
purkinje/assets.py
purkinje/config.py
purkinje/purkinje.py
purkinje.egg-info/PKG-INFO
purkinje.egg-info/SOURCES.txt
purkinje.egg-info/dependency_links.txt
purkinje.egg-info/entry_points.txt
purkinje.egg-info/not-zip-safe
purkinje.egg-info/requires.txt
purkinje.egg-info/top_level.txt
purkinje/static/bower_components/Chart.js/.bower.json
purkinje/static/bower_components/Chart.js/Chart.js
purkinje/static/bower_components/Chart.js/bower.json
purkinje/static/bower_components/angular/.bower.json
purkinje/static/bower_components/angular/README.md
purkinje/static/bower_components/angular/angular-csp.css
purkinje/static/bower_components/angular/angular.js
purkinje/static/bower_components/angular/angular.min.js
purkinje/static/bower_components/angular/angular.min.js.gzip
purkinje/static/bower_components/angular/angular.min.js.map
purkinje/static/bower_components/angular/bower.json
purkinje/static/bower_components/angular/index.js
purkinje/static/bower_components/angular/package.json
purkinje/static/bower_components/angular-bootstrap/.bower.json
purkinje/static/bower_components/angular-bootstrap/bower.json
purkinje/static/bower_components/angular-bootstrap/ui-bootstrap-tpls.js
purkinje/static/bower_components/angular-bootstrap/ui-bootstrap-tpls.min.js
purkinje/static/bower_components/angular-bootstrap/ui-bootstrap.js
purkinje/static/bower_components/angular-bootstrap/ui-bootstrap.min.js
purkinje/static/bower_components/angular-mocks/.bower.json
purkinje/static/bower_components/angular-mocks/README.md
purkinje/static/bower_components/angular-mocks/angular-mocks.js
purkinje/static/bower_components/angular-mocks/bower.json
purkinje/static/bower_components/angular-mocks/ngAnimateMock.js
purkinje/static/bower_components/angular-mocks/ngMock.js
purkinje/static/bower_components/angular-mocks/ngMockE2E.js
purkinje/static/bower_components/angular-mocks/package.json
purkinje/static/bower_components/angular-reconnecting-websocket/.bower.json
purkinje/static/bower_components/angular-reconnecting-websocket/Gruntfile.js
