Metadata-Version: 1.1
Name: purkinje
Version: 0.1.10
Summary: Test runner for py.test with web GUI
Home-page: https://github.com/bbiskup/purkinje
Author: Bernhard Biskup
Author-email: bbiskup@gmx.de
License: The MIT License (MIT)
Keywords: purkinje pytest testrunner websockets
Platform: UNKNOWN
Classifier: Development Status :: 2 - Pre-Alpha
Classifier: Environment :: Console
Classifier: Environment :: Web Environment
Classifier: Intended Audience :: Developers
Classifier: License :: OSI Approved :: MIT License
Classifier: Programming Language :: Python :: 2.7
Classifier: Topic :: Software Development :: Testing
